funcnodes/__init__.py
funcnodes/__main__.py
funcnodes/patches.py
funcnodes/cli/__init__.py
funcnodes/cli/interactive.py
funcnodes/cli/main.py
funcnodes/cli/parser.py
funcnodes/cli/runtime.py
funcnodes/cli/tasks.py
funcnodes/cli/utils.py
funcnodes/cli/worker.py
funcnodes/files/__init__.py
funcnodes/files/icon.icns
funcnodes/files/icon.ico
funcnodes/files/icon.png
funcnodes/runner/__init__.py
funcnodes/runner/_simple_server.py
funcnodes/runner/register.py
funcnodes/runner/standalone.py
funcnodes/utils/__init__.py
funcnodes/utils/asyncutils.py
funcnodes/utils/cmd.py
funcnodes/utils/lazy.py
funcnodes/worker/__init__.py
funcnodes/worker/worker_manager.py
funcnodes-1.5.1.dist-info/METADATA
funcnodes-1.5.1.dist-info/WHEEL
funcnodes-1.5.1.dist-info/entry_points.txt
funcnodes-1.5.1.dist-info/licenses/LICENSE
funcnodes-1.5.1.dist-info/RECORD
