Metadata-Version: 2.4
Name: funcnodes
Version: 1.5.1
Summary: funcnodes
Project-URL: homepage, https://github.com/Linkdlab/funcnodes
Project-URL: source, https://github.com/Linkdlab/funcnodes
Project-URL: tracker, https://github.com/Linkdlab/funcnodes/issues
Project-URL: download, https://pypi.org/project/funcnodes/#files
Author-email: Julian Kimmig <julian.kimmig@linkdlab.de>
License: AGPL-3.0
License-File: LICENSE
Classifier: Development Status :: 4 - Beta
Classifier: Intended Audience :: Developers
Classifier: Intended Audience :: Education
Classifier: Intended Audience :: Science/Research
Classifier: License :: OSI Approved :: GNU Affero General Public License v3 or later (AGPLv3+)
Requires-Python: >=3.11
Requires-Dist: funcnodes-basic>=0.2.1
Requires-Dist: funcnodes-core>=1.0.2
Requires-Dist: funcnodes-module; sys_platform != 'emscripten'
Requires-Dist: funcnodes-react-flow>=1.1.0; sys_platform != 'emscripten'
Requires-Dist: funcnodes-worker>=1.5.1; sys_platform == 'emscripten'
Requires-Dist: funcnodes-worker[all]>=1.5.1; sys_platform != 'emscripten'
Requires-Dist: rich>=14.2.0
Requires-Dist: subprocess-monitor>=0.3.0; sys_platform != 'emscripten'
Requires-Dist: uv>=0.5.21; sys_platform != 'emscripten'
Requires-Dist: venvmngr>=0.2.0; sys_platform != 'emscripten'
Requires-Dist: virtualenv; sys_platform != 'emscripten'
Provides-Extra: profile
Requires-Dist: yappi>=1.6.10; extra == 'profile'
Provides-Extra: profiling
Requires-Dist: yappi>=1.6.10; extra == 'profiling'
